README.md
pyproject.toml
setup.py
col/__init__.py
col/collection.py
col/sandbox.py
col.egg-info/PKG-INFO
col.egg-info/SOURCES.txt
col.egg-info/dependency_links.txt
col.egg-info/top_level.txt