Metadata-Version: 1.2
Name: col
Version: 0.0.1
Summary: Collections for Python
Home-page: https://github.com/daanklijn/col
Author: Daan Klijn
Author-email: daanklijn0@gmail.com
License: UNKNOWN
Platform: UNKNOWN
Requires-Python: >=3.6
